conditional_context/__init__.py
conditional_context/__meta__.py
conditional_context/__pycache__/__init__.cpython-36.pyc
conditional_context/__pycache__/__init__.cpython-38.pyc
conditional_context-1.1.0.dist-info/LICENSE
conditional_context-1.1.0.dist-info/METADATA
conditional_context-1.1.0.dist-info/WHEEL
conditional_context-1.1.0.dist-info/top_level.txt
conditional_context-1.1.0.dist-info/RECORD
