Metadata-Version: 2.1
Name: conditional-context
Version: 1.1.0
Summary: Context manager that will skip the body on a condition.
Home-page: https://github.com/justengel/conditional_context
Author: Justin Engel
Author-email: jtengel08@gmail.com
License: MIT
Download-URL: https://github.com/justengel/conditional_context/archive/v1.1.0.tar.gz
Keywords: conditional context skip context
Platform: any
Classifier: Programming Language :: Python
Classifier: Programming Language :: Python :: 3
Classifier: Operating System :: OS Independent
